{"upload_date": "20150427", "creator": null, "format_note": "hd720", "height": 720, "thumbnail": "https://i.ytimg.com/vi/VNiRcRQVkJY/hqdefault.jpg", "like_count": 4, "duration": 27, "fulltitle": "Promo: La asombrosa excursi\u00f3n de Zamba al mundo de la alimentaci\u00f3n - Canal Pakapaka", "playlist_index": 200, "view_count": 1821, "playlist": "Uploads from CanalPakapaka", "title": "Promo: La asombrosa excursi\u00f3n de Zamba al mundo de la alimentaci\u00f3n - Canal Pakapaka", "_filename": "downloads\\CanalPakapaka\\Promo - La asombrosa excursi\u00f3n de Zamba al mundo de la alimentaci\u00f3n - Canal Pakapaka-VNiRcRQVkJY.mp4", "tags": [], "is_live": null, "id": "VNiRcRQVkJY", "dislike_count": 2, "average_rating": 3.66666674614, "filesize": null, "fps": null, "age_limit": 0, "annotations": "<?xml version=\"1.0\" encoding=\"UTF-8\" ?><document><annotations></annotations></document>", "webpage_url_basename": "VNiRcRQVkJY", "acodec": "avc1.64001F", "display_id": "VNiRcRQVkJY", "automatic_captions": {}, "description": "", "format": "22 - 1280x720 (hd720)", "start_time": null, "tbr": null, "categories": ["Education"], "playlist_id": "UUVVNYxncuD4EfHpKDlPIYcQ", "uploader": "CanalPakapaka", "format_id": "22", "uploader_id": "CanalPakapaka", "subtitles": {}, "playlist_title": "Uploads from CanalPakapaka", "thumbnails": [{"url": "https://i.ytimg.com/vi/VNiRcRQVkJY/hqdefault.jpg", "id": "0"}], "alt_title": null, "url": "https://r7---sn-j5cax8pnpvo-x1x6.googlevideo.com/videoplayback?initcwndbps=1265000&signature=2EA1C733CFE6D8CC38E373F052383B46AB301FA5.AFE037D312FA552C270CDACD85899A537D6613A2&dur=26.865&sver=3&sparams=dur%2Cid%2Cinitcwndbps%2Cip%2Cipbits%2Citag%2Clmt%2Cmime%2Cmm%2Cmn%2Cms%2Cmv%2Cpcm2%2Cpcm2cms%2Cpl%2Cratebypass%2Crequiressl%2Csource%2Cupn%2Cexpire&lmt=1430146799200234&pcm2=yes&pcm2cms=yes&mime=video%2Fmp4&ip=181.169.199.112&requiressl=yes&mm=31&source=youtube&pl=20&mn=sn-j5cax8pnpvo-x1x6&mt=1451805828&mv=m&id=o-ANhq0Qc3DOszJWfMJQXdPA_193KllZnyHQD-WPZ9G1-6&ms=au&expire=1451827480&key=yt6&upn=-PI7yCUmRHw&ratebypass=yes&ipbits=0&itag=22&fexp=9407157%2C9412858%2C9413278%2C9416126%2C9418200%2C9420452%2C9422124%2C9422541%2C9422596%2C9422925%2C9423573%2C9423590%2C9423662%2C9424020%2C9425346%2C9426236", "extractor_key": "Youtube", "vcodec": " mp4a.40.2", "http_headers": {"Accept-Charset": "ISO-8859-1,utf-8;q=0.7,*;q=0.7", "Accept-Language": "en-us,en;q=0.5", "Accept-Encoding": "gzip, deflate", "Accept": "text/html,application/xhtml+xml,application/xml;q=0.9,*/*;q=0.8", "User-Agent": "Mozilla/5.0 (X11; Linux x86_64; rv:10.0) Gecko/20150101 Firefox/20.0 (Chrome)"}, "player_url": null, "ext": "mp4", "extractor": "youtube", "end_time": null, "webpage_url": "https://www.youtube.com/watch?v=VNiRcRQVkJY", "formats": [{"http_headers": {"Accept-Charset": "ISO-8859-1,utf-8;q=0.7,*;q=0.7", "Accept-Language": "en-us,en;q=0.5", "Accept-Encoding": "gzip, deflate", "Accept": "text/html,application/xhtml+xml,application/xml;q=0.9,*/*;q=0.8", "User-Agent": "Mozilla/5.0 (X11; Linux x86_64; rv:10.0) Gecko/20150101 Firefox/20.0 (Chrome)"}, "tbr": 53.531, "format": "249 - audio only (DASH audio)", "url": "https://r7---sn-j5cax8pnpvo-x1x6.googlevideo.com/videoplayback?initcwndbps=1265000&signature=B51025AEFE89C8581BFCB1E707934701B0500D4C.B6F0D47C6D883F34EFA3A80627C4E13814661705&dur=26.801&ipbits=0&sver=3&gir=yes&sparams=clen%2Cdur%2Cgir%2Cid%2Cinitcwndbps%2Cip%2Cipbits%2Citag%2Ckeepalive%2Clmt%2Cmime%2Cmm%2Cmn%2Cms%2Cmv%2Cpcm2%2Cpcm2cms%2Cpl%2Crequiressl%2Csource%2Cupn%2Cexpire&lmt=1430476371729414&pcm2=yes&pcm2cms=yes&mime=audio%2Fwebm&ip=181.169.199.112&requiressl=yes&mm=31&source=youtube&pl=20&mn=sn-j5cax8pnpvo-x1x6&mt=1451805828&mv=m&id=o-ANhq0Qc3DOszJWfMJQXdPA_193KllZnyHQD-WPZ9G1-6&ms=au&expire=1451827480&key=yt6&upn=-PI7yCUmRHw&keepalive=yes&itag=249&clen=178267&fexp=9407157%2C9412858%2C9413278%2C9416126%2C9418200%2C9420452%2C9422124%2C9422541%2C9422596%2C9422925%2C9423573%2C9423590%2C9423662%2C9424020%2C9425346%2C9426236&ratebypass=yes", "vcodec": "none", "format_note": "DASH audio", "abr": 50, "preference": -50, "height": null, "width": null, "ext": "webm", "filesize": 178267, "fps": null, "format_id": "249", "player_url": null, "acodec": "opus"}, {"http_headers": {"Accept-Charset": "ISO-8859-1,utf-8;q=0.7,*;q=0.7", "Accept-Language": "en-us,en;q=0.5", "Accept-Encoding": "gzip, deflate", "Accept": "text/html,application/xhtml+xml,application/xml;q=0.9,*/*;q=0.8", "User-Agent": "Mozilla/5.0 (X11; Linux x86_64; rv:10.0) Gecko/20150101 Firefox/20.0 (Chrome)"}, "tbr": 68.104, "format": "250 - audio only (DASH audio)", "url": "https://r7---sn-j5cax8pnpvo-x1x6.googlevideo.com/videoplayback?initcwndbps=1265000&signature=C51C8A3C2344147EB19214DEC4EF416C167DBABF.8811FB0952B865A1C48778B068534471962C2857&dur=26.801&ipbits=0&sver=3&gir=yes&sparams=clen%2Cdur%2Cgir%2Cid%2Cinitcwndbps%2Cip%2Cipbits%2Citag%2Ckeepalive%2Clmt%2Cmime%2Cmm%2Cmn%2Cms%2Cmv%2Cpcm2%2Cpcm2cms%2Cpl%2Crequiressl%2Csource%2Cupn%2Cexpire&lmt=1430476260424319&pcm2=yes&pcm2cms=yes&mime=audio%2Fwebm&ip=181.169.199.112&requiressl=yes&mm=31&source=youtube&pl=20&mn=sn-j5cax8pnpvo-x1x6&mt=1451805828&mv=m&id=o-ANhq0Qc3DOszJWfMJQXdPA_193KllZnyHQD-WPZ9G1-6&ms=au&expire=1451827480&key=yt6&upn=-PI7yCUmRHw&keepalive=yes&itag=250&clen=224422&fexp=9407157%2C9412858%2C9413278%2C9416126%2C9418200%2C9420452%2C9422124%2C9422541%2C9422596%2C9422925%2C9423573%2C9423590%2C9423662%2C9424020%2C9425346%2C9426236&ratebypass=yes", "vcodec": "none", "format_note": "DASH audio", "abr": 70, "preference": -50, "height": null, "width": null, "ext": "webm", "filesize": 224422, "fps": null, "format_id": "250", "player_url": null, "acodec": "opus"}, {"asr": 44100, "tbr": 104, "format": "171 - audio only (DASH audio)", "url": "https://r7---sn-j5cax8pnpvo-x1x6.googlevideo.com/videoplayback?id=54d8917114159096&itag=171&source=youtube&requiressl=yes&mn=sn-j5cax8pnpvo-x1x6&ms=au&mv=m&pl=20&mm=31&pcm2cms=yes&ratebypass=yes&mime=audio/webm&gir=yes&clen=348567&lmt=1430476371932670&dur=26.794&upn=uCSu53jSZcQ&signature=6B34C7D1187E8D3219BB94A20659412624B2AD28.70217FAA538B14DAE795766D4DC19D0E1A59BE1F&mt=1451805828&fexp=9407157,9412858,9413278,9416126,9418200,9420452,9422124,9422541,9422596,9422925,9423573,9423590,9423662,9424020,9425346,9426236&key=dg_yt0&sver=3&ip=181.169.199.112&ipbits=0&expire=1451827480&sparams=ip,ipbits,expire,id,itag,source,requiressl,mn,ms,mv,pl,mm,pcm2cms,ratebypass,mime,gir,clen,lmt,dur", "vcodec": "none", "format_note": "DASH audio", "ext": "webm", "height": null, "width": null, "abr": 128, "preference": -50, "fps": null, "format_id": "171", "acodec": "vorbis", "http_headers": {"Accept-Charset": "ISO-8859-1,utf-8;q=0.7,*;q=0.7", "Accept-Language": "en-us,en;q=0.5", "Accept-Encoding": "gzip, deflate", "Accept": "text/html,application/xhtml+xml,application/xml;q=0.9,*/*;q=0.8", "User-Agent": "Mozilla/5.0 (X11; Linux x86_64; rv:10.0) Gecko/20150101 Firefox/20.0 (Chrome)"}, "filesize": 348567}, {"http_headers": {"Accept-Charset": "ISO-8859-1,utf-8;q=0.7,*;q=0.7", "Accept-Language": "en-us,en;q=0.5", "Accept-Encoding": "gzip, deflate", "Accept": "text/html,application/xhtml+xml,application/xml;q=0.9,*/*;q=0.8", "User-Agent": "Mozilla/5.0 (X11; Linux x86_64; rv:10.0) Gecko/20150101 Firefox/20.0 (Chrome)"}, "tbr": 120.111, "format": "251 - audio only (DASH audio)", "url": "https://r7---sn-j5cax8pnpvo-x1x6.googlevideo.com/videoplayback?initcwndbps=1265000&signature=6A0E405949AAEE46159A7295B045D3309D5C933C.0463583850D4804EF64C60542565EE705D8D9B1C&dur=26.801&ipbits=0&sver=3&gir=yes&sparams=clen%2Cdur%2Cgir%2Cid%2Cinitcwndbps%2Cip%2Cipbits%2Citag%2Ckeepalive%2Clmt%2Cmime%2Cmm%2Cmn%2Cms%2Cmv%2Cpcm2%2Cpcm2cms%2Cpl%2Crequiressl%2Csource%2Cupn%2Cexpire&lmt=1430476370271358&pcm2=yes&pcm2cms=yes&mime=audio%2Fwebm&ip=181.169.199.112&requiressl=yes&mm=31&source=youtube&pl=20&mn=sn-j5cax8pnpvo-x1x6&mt=1451805828&mv=m&id=o-ANhq0Qc3DOszJWfMJQXdPA_193KllZnyHQD-WPZ9G1-6&ms=au&expire=1451827480&key=yt6&upn=-PI7yCUmRHw&keepalive=yes&itag=251&clen=394779&fexp=9407157%2C9412858%2C9413278%2C9416126%2C9418200%2C9420452%2C9422124%2C9422541%2C9422596%2C9422925%2C9423573%2C9423590%2C9423662%2C9424020%2C9425346%2C9426236&ratebypass=yes", "vcodec": "none", "format_note": "DASH audio", "abr": 160, "preference": -50, "height": null, "width": null, "ext": "webm", "filesize": 394779, "fps": null, "format_id": "251", "player_url": null, "acodec": "opus"}, {"asr": 44100, "tbr": 129, "container": "m4a_dash", "format": "140 - audio only (DASH audio)", "url": "https://r7---sn-j5cax8pnpvo-x1x6.googlevideo.com/videoplayback?id=54d8917114159096&itag=140&source=youtube&requiressl=yes&mn=sn-j5cax8pnpvo-x1x6&ms=au&mv=m&pl=20&mm=31&pcm2cms=yes&ratebypass=yes&mime=audio/mp4&gir=yes&clen=432149&lmt=1430146769143490&dur=26.865&upn=uCSu53jSZcQ&signature=5D6E4D11C62C8354B0F21A5619F8C06306610F2F.54E6D338E9B43BF980EE2187A675EC2204AC6AA0&mt=1451805828&fexp=9407157,9412858,9413278,9416126,9418200,9420452,9422124,9422541,9422596,9422925,9423573,9423590,9423662,9424020,9425346,9426236&key=dg_yt0&sver=3&ip=181.169.199.112&ipbits=0&expire=1451827480&sparams=ip,ipbits,expire,id,itag,source,requiressl,mn,ms,mv,pl,mm,pcm2cms,ratebypass,mime,gir,clen,lmt,dur", "filesize": 432149, "vcodec": "none", "format_note": "DASH audio", "abr": 128, "height": null, "width": null, "ext": "m4a", "preference": -50, "fps": null, "format_id": "140", "http_headers": {"Accept-Charset": "ISO-8859-1,utf-8;q=0.7,*;q=0.7", "Accept-Language": "en-us,en;q=0.5", "Accept-Encoding": "gzip, deflate", "Accept": "text/html,application/xhtml+xml,application/xml;q=0.9,*/*;q=0.8", "User-Agent": "Mozilla/5.0 (X11; Linux x86_64; rv:10.0) Gecko/20150101 Firefox/20.0 (Chrome)"}, "acodec": "aac"}, {"asr": 44100, "tbr": 255, "container": "m4a_dash", "format": "141 - audio only (DASH audio)", "url": "https://r7---sn-j5cax8pnpvo-x1x6.googlevideo.com/videoplayback?id=54d8917114159096&itag=141&source=youtube&requiressl=yes&mn=sn-j5cax8pnpvo-x1x6&ms=au&mv=m&pl=20&mm=31&pcm2cms=yes&ratebypass=yes&mime=audio/mp4&gir=yes&clen=857184&lmt=1430146767503391&dur=26.865&upn=uCSu53jSZcQ&signature=7EA3D8BEB4C5DE06D86F25D583727D26C5ECCB45.13313E585AEE5E754A0463D428A46126AD59E757&mt=1451805828&fexp=9407157,9412858,9413278,9416126,9418200,9420452,9422124,9422541,9422596,9422925,9423573,9423590,9423662,9424020,9425346,9426236&key=dg_yt0&sver=3&ip=181.169.199.112&ipbits=0&expire=1451827480&sparams=ip,ipbits,expire,id,itag,source,requiressl,mn,ms,mv,pl,mm,pcm2cms,ratebypass,mime,gir,clen,lmt,dur", "filesize": 857184, "vcodec": "none", "format_note": "DASH audio", "abr": 256, "height": null, "width": null, "ext": "m4a", "preference": -50, "fps": null, "format_id": "141", "http_headers": {"Accept-Charset": "ISO-8859-1,utf-8;q=0.7,*;q=0.7", "Accept-Language": "en-us,en;q=0.5", "Accept-Encoding": "gzip, deflate", "Accept": "text/html,application/xhtml+xml,application/xml;q=0.9,*/*;q=0.8", "User-Agent": "Mozilla/5.0 (X11; Linux x86_64; rv:10.0) Gecko/20150101 Firefox/20.0 (Chrome)"}, "acodec": "aac"}, {"asr": null, "tbr": 88, "container": "webm", "format": "278 - 256x144 (DASH video)", "url": "https://r7---sn-j5cax8pnpvo-x1x6.googlevideo.com/videoplayback?id=54d8917114159096&itag=278&source=youtube&requiressl=yes&mn=sn-j5cax8pnpvo-x1x6&ms=au&mv=m&pl=20&mm=31&pcm2cms=yes&ratebypass=yes&mime=video/webm&gir=yes&clen=261219&lmt=1430476374901278&dur=26.720&upn=uCSu53jSZcQ&signature=5556EDCD0961934A8FA117E7610828E4EB46B49A.8385CB09F49251ED4ABAF25A1D4CC08A126FB01B&mt=1451805828&fexp=9407157,9412858,9413278,9416126,9418200,9420452,9422124,9422541,9422596,9422925,9423573,9423590,9423662,9424020,9425346,9426236&key=dg_yt0&sver=3&ip=181.169.199.112&ipbits=0&expire=1451827480&sparams=ip,ipbits,expire,id,itag,source,requiressl,mn,ms,mv,pl,mm,pcm2cms,ratebypass,mime,gir,clen,lmt,dur", "filesize": 261219, "vcodec": "vp9", "format_note": "DASH video", "height": 144, "width": 256, "ext": "webm", "preference": -40, "fps": 13, "format_id": "278", "http_headers": {"Accept-Charset": "ISO-8859-1,utf-8;q=0.7,*;q=0.7", "Accept-Language": "en-us,en;q=0.5", "Accept-Encoding": "gzip, deflate", "Accept": "text/html,application/xhtml+xml,application/xml;q=0.9,*/*;q=0.8", "User-Agent": "Mozilla/5.0 (X11; Linux x86_64; rv:10.0) Gecko/20150101 Firefox/20.0 (Chrome)"}, "acodec": "none"}, {"asr": null, "tbr": 110, "format": "160 - 256x144 (DASH video)", "url": "https://r7---sn-j5cax8pnpvo-x1x6.googlevideo.com/videoplayback?id=54d8917114159096&itag=160&source=youtube&requiressl=yes&mn=sn-j5cax8pnpvo-x1x6&ms=au&mv=m&pl=20&mm=31&pcm2cms=yes&ratebypass=yes&mime=video/mp4&gir=yes&clen=366095&lmt=1430146775921261&dur=26.800&upn=uCSu53jSZcQ&signature=7788653F234C309BABC103D51F0D1B826190762F.237AA8703FA45F5F456757DF87CD8BB5E0EA90AE&mt=1451805828&fexp=9407157,9412858,9413278,9416126,9418200,9420452,9422124,9422541,9422596,9422925,9423573,9423590,9423662,9424020,9425346,9426236&key=dg_yt0&sver=3&ip=181.169.199.112&ipbits=0&expire=1451827480&sparams=ip,ipbits,expire,id,itag,source,requiressl,mn,ms,mv,pl,mm,pcm2cms,ratebypass,mime,gir,clen,lmt,dur", "filesize": 366095, "vcodec": "avc1.42c00c", "format_note": "DASH video", "height": 144, "width": 256, "ext": "mp4", "preference": -40, "fps": 13, "format_id": "160", "http_headers": {"Accept-Charset": "ISO-8859-1,utf-8;q=0.7,*;q=0.7", "Accept-Language": "en-us,en;q=0.5", "Accept-Encoding": "gzip, deflate", "Accept": "text/html,application/xhtml+xml,application/xml;q=0.9,*/*;q=0.8", "User-Agent": "Mozilla/5.0 (X11; Linux x86_64; rv:10.0) Gecko/20150101 Firefox/20.0 (Chrome)"}, "acodec": "none"}, {"asr": null, "tbr": 219, "format": "242 - 426x240 (DASH video)", "url": "https://r7---sn-j5cax8pnpvo-x1x6.googlevideo.com/videoplayback?id=54d8917114159096&itag=242&source=youtube&requiressl=yes&mn=sn-j5cax8pnpvo-x1x6&ms=au&mv=m&pl=20&mm=31&pcm2cms=yes&ratebypass=yes&mime=video/webm&gir=yes&clen=599754&lmt=1430476372085074&dur=26.760&upn=uCSu53jSZcQ&signature=62C28E6EA76662F4E68E3B30CBEE88C83AAF21D7.807AF8649F226A6728EE48B401D5F6673EA5EF7F&mt=1451805828&fexp=9407157,9412858,9413278,9416126,9418200,9420452,9422124,9422541,9422596,9422925,9423573,9423590,9423662,9424020,9425346,9426236&key=dg_yt0&sver=3&ip=181.169.199.112&ipbits=0&expire=1451827480&sparams=ip,ipbits,expire,id,itag,source,requiressl,mn,ms,mv,pl,mm,pcm2cms,ratebypass,mime,gir,clen,lmt,dur", "filesize": 599754, "vcodec": "vp9", "format_note": "DASH video", "height": 240, "width": 426, "ext": "webm", "preference": -40, "fps": 25, "format_id": "242", "http_headers": {"Accept-Charset": "ISO-8859-1,utf-8;q=0.7,*;q=0.7", "Accept-Language": "en-us,en;q=0.5", "Accept-Encoding": "gzip, deflate", "Accept": "text/html,application/xhtml+xml,application/xml;q=0.9,*/*;q=0.8", "User-Agent": "Mozilla/5.0 (X11; Linux x86_64; rv:10.0) Gecko/20150101 Firefox/20.0 (Chrome)"}, "acodec": "none"}, {"asr": null, "tbr": 246, "format": "133 - 426x240 (DASH video)", "url": "https://r7---sn-j5cax8pnpvo-x1x6.googlevideo.com/videoplayback?id=54d8917114159096&itag=133&source=youtube&requiressl=yes&mn=sn-j5cax8pnpvo-x1x6&ms=au&mv=m&pl=20&mm=31&pcm2cms=yes&ratebypass=yes&mime=video/mp4&gir=yes&clen=817955&lmt=1430146771592233&dur=26.800&upn=uCSu53jSZcQ&signature=54B9914961AA4319008E448A910262D48960CB49.3D48749FE065811C338431B2C1B90F034354F0AA&mt=1451805828&fexp=9407157,9412858,9413278,9416126,9418200,9420452,9422124,9422541,9422596,9422925,9423573,9423590,9423662,9424020,9425346,9426236&key=dg_yt0&sver=3&ip=181.169.199.112&ipbits=0&expire=1451827480&sparams=ip,ipbits,expire,id,itag,source,requiressl,mn,ms,mv,pl,mm,pcm2cms,ratebypass,mime,gir,clen,lmt,dur", "filesize": 817955, "vcodec": "avc1.4d4015", "format_note": "DASH video", "height": 240, "width": 426, "ext": "mp4", "preference": -40, "fps": 25, "format_id": "133", "http_headers": {"Accept-Charset": "ISO-8859-1,utf-8;q=0.7,*;q=0.7", "Accept-Language": "en-us,en;q=0.5", "Accept-Encoding": "gzip, deflate", "Accept": "text/html,application/xhtml+xml,application/xml;q=0.9,*/*;q=0.8", "User-Agent": "Mozilla/5.0 (X11; Linux x86_64; rv:10.0) Gecko/20150101 Firefox/20.0 (Chrome)"}, "acodec": "none"}, {"asr": null, "tbr": 377, "format": "243 - 640x360 (DASH video)", "url": "https://r7---sn-j5cax8pnpvo-x1x6.googlevideo.com/videoplayback?id=54d8917114159096&itag=243&source=youtube&requiressl=yes&mn=sn-j5cax8pnpvo-x1x6&ms=au&mv=m&pl=20&mm=31&pcm2cms=yes&ratebypass=yes&mime=video/webm&gir=yes&clen=1037186&lmt=1430476372881192&dur=26.760&upn=uCSu53jSZcQ&signature=47BCBB9BE19249E613B62F6C36945B0586F91D31.836E2A4826E7A46C248462EE62EADD515FF9B47E&mt=1451805828&fexp=9407157,9412858,9413278,9416126,9418200,9420452,9422124,9422541,9422596,9422925,9423573,9423590,9423662,9424020,9425346,9426236&key=dg_yt0&sver=3&ip=181.169.199.112&ipbits=0&expire=1451827480&sparams=ip,ipbits,expire,id,itag,source,requiressl,mn,ms,mv,pl,mm,pcm2cms,ratebypass,mime,gir,clen,lmt,dur", "filesize": 1037186, "vcodec": "vp9", "format_note": "DASH video", "height": 360, "width": 640, "ext": "webm", "preference": -40, "fps": 25, "format_id": "243", "http_headers": {"Accept-Charset": "ISO-8859-1,utf-8;q=0.7,*;q=0.7", "Accept-Language": "en-us,en;q=0.5", "Accept-Encoding": "gzip, deflate", "Accept": "text/html,application/xhtml+xml,application/xml;q=0.9,*/*;q=0.8", "User-Agent": "Mozilla/5.0 (X11; Linux x86_64; rv:10.0) Gecko/20150101 Firefox/20.0 (Chrome)"}, "acodec": "none"}, {"asr": null, "tbr": 554, "format": "244 - 854x480 (DASH video)", "url": "https://r7---sn-j5cax8pnpvo-x1x6.googlevideo.com/videoplayback?id=54d8917114159096&itag=244&source=youtube&requiressl=yes&mn=sn-j5cax8pnpvo-x1x6&ms=au&mv=m&pl=20&mm=31&pcm2cms=yes&ratebypass=yes&mime=video/webm&gir=yes&clen=1647707&lmt=1430476372326606&dur=26.760&upn=uCSu53jSZcQ&signature=711C0AE7FE41298B92B075FED978F177806E0245.6C74EDFF6BB71724C2B940FCFF3166F06748621D&mt=1451805828&fexp=9407157,9412858,9413278,9416126,9418200,9420452,9422124,9422541,9422596,9422925,9423573,9423590,9423662,9424020,9425346,9426236&key=dg_yt0&sver=3&ip=181.169.199.112&ipbits=0&expire=1451827480&sparams=ip,ipbits,expire,id,itag,source,requiressl,mn,ms,mv,pl,mm,pcm2cms,ratebypass,mime,gir,clen,lmt,dur", "filesize": 1647707, "vcodec": "vp9", "format_note": "DASH video", "height": 480, "width": 854, "ext": "webm", "preference": -40, "fps": 25, "format_id": "244", "http_headers": {"Accept-Charset": "ISO-8859-1,utf-8;q=0.7,*;q=0.7", "Accept-Language": "en-us,en;q=0.5", "Accept-Encoding": "gzip, deflate", "Accept": "text/html,application/xhtml+xml,application/xml;q=0.9,*/*;q=0.8", "User-Agent": "Mozilla/5.0 (X11; Linux x86_64; rv:10.0) Gecko/20150101 Firefox/20.0 (Chrome)"}, "acodec": "none"}, {"asr": null, "tbr": 560, "format": "134 - 640x360 (DASH video)", "url": "https://r7---sn-j5cax8pnpvo-x1x6.googlevideo.com/videoplayback?id=54d8917114159096&itag=134&source=youtube&requiressl=yes&mn=sn-j5cax8pnpvo-x1x6&ms=au&mv=m&pl=20&mm=31&pcm2cms=yes&ratebypass=yes&mime=video/mp4&gir=yes&clen=1356628&lmt=1430146776451602&dur=26.800&upn=uCSu53jSZcQ&signature=358DEBCC7C0DC893A068F3C5B8044D6E6E31BABD.603636273DDD013E75B7458BA2442F05F86DDBDD&mt=1451805828&fexp=9407157,9412858,9413278,9416126,9418200,9420452,9422124,9422541,9422596,9422925,9423573,9423590,9423662,9424020,9425346,9426236&key=dg_yt0&sver=3&ip=181.169.199.112&ipbits=0&expire=1451827480&sparams=ip,ipbits,expire,id,itag,source,requiressl,mn,ms,mv,pl,mm,pcm2cms,ratebypass,mime,gir,clen,lmt,dur", "filesize": 1356628, "vcodec": "avc1.4d401e", "format_note": "DASH video", "height": 360, "width": 640, "ext": "mp4", "preference": -40, "fps": 25, "format_id": "134", "http_headers": {"Accept-Charset": "ISO-8859-1,utf-8;q=0.7,*;q=0.7", "Accept-Language": "en-us,en;q=0.5", "Accept-Encoding": "gzip, deflate", "Accept": "text/html,application/xhtml+xml,application/xml;q=0.9,*/*;q=0.8", "User-Agent": "Mozilla/5.0 (X11; Linux x86_64; rv:10.0) Gecko/20150101 Firefox/20.0 (Chrome)"}, "acodec": "none"}, {"asr": null, "tbr": 987, "format": "135 - 854x480 (DASH video)", "url": "https://r7---sn-j5cax8pnpvo-x1x6.googlevideo.com/videoplayback?id=54d8917114159096&itag=135&source=youtube&requiressl=yes&mn=sn-j5cax8pnpvo-x1x6&ms=au&mv=m&pl=20&mm=31&pcm2cms=yes&ratebypass=yes&mime=video/mp4&gir=yes&clen=2545679&lmt=1430146775759982&dur=26.800&upn=uCSu53jSZcQ&signature=60CD5E0C6165B581D93BD0387CA009BF757E6E4A.21CE5D41D77F820F085B572D0200B1CB84A59BED&mt=1451805828&fexp=9407157,9412858,9413278,9416126,9418200,9420452,9422124,9422541,9422596,9422925,9423573,9423590,9423662,9424020,9425346,9426236&key=dg_yt0&sver=3&ip=181.169.199.112&ipbits=0&expire=1451827480&sparams=ip,ipbits,expire,id,itag,source,requiressl,mn,ms,mv,pl,mm,pcm2cms,ratebypass,mime,gir,clen,lmt,dur", "filesize": 2545679, "vcodec": "avc1.4d401e", "format_note": "DASH video", "height": 480, "width": 854, "ext": "mp4", "preference": -40, "fps": 25, "format_id": "135", "http_headers": {"Accept-Charset": "ISO-8859-1,utf-8;q=0.7,*;q=0.7", "Accept-Language": "en-us,en;q=0.5", "Accept-Encoding": "gzip, deflate", "Accept": "text/html,application/xhtml+xml,application/xml;q=0.9,*/*;q=0.8", "User-Agent": "Mozilla/5.0 (X11; Linux x86_64; rv:10.0) Gecko/20150101 Firefox/20.0 (Chrome)"}, "acodec": "none"}, {"asr": null, "tbr": 1095, "format": "247 - 1280x720 (DASH video)", "url": "https://r7---sn-j5cax8pnpvo-x1x6.googlevideo.com/videoplayback?id=54d8917114159096&itag=247&source=youtube&requiressl=yes&mn=sn-j5cax8pnpvo-x1x6&ms=au&mv=m&pl=20&mm=31&pcm2cms=yes&ratebypass=yes&mime=video/webm&gir=yes&clen=3244835&lmt=1430476373202239&dur=26.760&upn=uCSu53jSZcQ&signature=352DB72898708E0A0B1E1316A5345A91D19FEC19.01BDA551F9B5C0A0B9E88C64D432AA78FDA3C345&mt=1451805828&fexp=9407157,9412858,9413278,9416126,9418200,9420452,9422124,9422541,9422596,9422925,9423573,9423590,9423662,9424020,9425346,9426236&key=dg_yt0&sver=3&ip=181.169.199.112&ipbits=0&expire=1451827480&sparams=ip,ipbits,expire,id,itag,source,requiressl,mn,ms,mv,pl,mm,pcm2cms,ratebypass,mime,gir,clen,lmt,dur", "filesize": 3244835, "vcodec": "vp9", "format_note": "DASH video", "height": 720, "width": 1280, "ext": "webm", "preference": -40, "fps": 25, "format_id": "247", "http_headers": {"Accept-Charset": "ISO-8859-1,utf-8;q=0.7,*;q=0.7", "Accept-Language": "en-us,en;q=0.5", "Accept-Encoding": "gzip, deflate", "Accept": "text/html,application/xhtml+xml,application/xml;q=0.9,*/*;q=0.8", "User-Agent": "Mozilla/5.0 (X11; Linux x86_64; rv:10.0) Gecko/20150101 Firefox/20.0 (Chrome)"}, "acodec": "none"}, {"asr": null, "tbr": 1723, "format": "136 - 1280x720 (DASH video)", "url": "https://r7---sn-j5cax8pnpvo-x1x6.googlevideo.com/videoplayback?id=54d8917114159096&itag=136&source=youtube&requiressl=yes&mn=sn-j5cax8pnpvo-x1x6&ms=au&mv=m&pl=20&mm=31&pcm2cms=yes&ratebypass=yes&mime=video/mp4&gir=yes&clen=4792675&lmt=1430146783745077&dur=26.800&upn=uCSu53jSZcQ&signature=0C9319FBB1DDAB83EAAEBAB9E96927062FCC4783.5AA1F073CC0F1E3ECAA5ACADF387A2CBA72B8F1A&mt=1451805828&fexp=9407157,9412858,9413278,9416126,9418200,9420452,9422124,9422541,9422596,9422925,9423573,9423590,9423662,9424020,9425346,9426236&key=dg_yt0&sver=3&ip=181.169.199.112&ipbits=0&expire=1451827480&sparams=ip,ipbits,expire,id,itag,source,requiressl,mn,ms,mv,pl,mm,pcm2cms,ratebypass,mime,gir,clen,lmt,dur", "filesize": 4792675, "vcodec": "avc1.4d401f", "format_note": "DASH video", "height": 720, "width": 1280, "ext": "mp4", "preference": -40, "fps": 25, "format_id": "136", "http_headers": {"Accept-Charset": "ISO-8859-1,utf-8;q=0.7,*;q=0.7", "Accept-Language": "en-us,en;q=0.5", "Accept-Encoding": "gzip, deflate", "Accept": "text/html,application/xhtml+xml,application/xml;q=0.9,*/*;q=0.8", "User-Agent": "Mozilla/5.0 (X11; Linux x86_64; rv:10.0) Gecko/20150101 Firefox/20.0 (Chrome)"}, "acodec": "none"}, {"http_headers": {"Accept-Charset": "ISO-8859-1,utf-8;q=0.7,*;q=0.7", "Accept-Language": "en-us,en;q=0.5", "Accept-Encoding": "gzip, deflate", "Accept": "text/html,application/xhtml+xml,application/xml;q=0.9,*/*;q=0.8", "User-Agent": "Mozilla/5.0 (X11; Linux x86_64; rv:10.0) Gecko/20150101 Firefox/20.0 (Chrome)"}, "tbr": null, "format": "17 - 176x144 (small)", "url": "https://r7---sn-j5cax8pnpvo-x1x6.googlevideo.com/videoplayback?initcwndbps=1265000&signature=717BA504EA7F567576114153EEB9839BFB4DAC03.D19413CE1E4126A88378DC147496AA70A61FAD6E&dur=26.981&sver=3&sparams=dur%2Cid%2Cinitcwndbps%2Cip%2Cipbits%2Citag%2Clmt%2Cmime%2Cmm%2Cmn%2Cms%2Cmv%2Cpcm2%2Cpcm2cms%2Cpl%2Crequiressl%2Csource%2Cupn%2Cexpire&lmt=1430146561024054&pcm2=yes&pcm2cms=yes&mime=video%2F3gpp&ip=181.169.199.112&requiressl=yes&mm=31&source=youtube&pl=20&mn=sn-j5cax8pnpvo-x1x6&mt=1451805828&mv=m&id=o-ANhq0Qc3DOszJWfMJQXdPA_193KllZnyHQD-WPZ9G1-6&ms=au&expire=1451827480&key=yt6&upn=-PI7yCUmRHw&ipbits=0&itag=17&fexp=9407157%2C9412858%2C9413278%2C9416126%2C9418200%2C9420452%2C9422124%2C9422541%2C9422596%2C9422925%2C9423573%2C9423590%2C9423662%2C9424020%2C9425346%2C9426236&ratebypass=yes", "vcodec": " mp4a.40.2", "format_note": "small", "height": 144, "width": 176, "ext": "3gp", "filesize": null, "fps": null, "format_id": "17", "player_url": null, "acodec": "mp4v.20.3"}, {"http_headers": {"Accept-Charset": "ISO-8859-1,utf-8;q=0.7,*;q=0.7", "Accept-Language": "en-us,en;q=0.5", "Accept-Encoding": "gzip, deflate", "Accept": "text/html,application/xhtml+xml,application/xml;q=0.9,*/*;q=0.8", "User-Agent": "Mozilla/5.0 (X11; Linux x86_64; rv:10.0) Gecko/20150101 Firefox/20.0 (Chrome)"}, "tbr": null, "format": "36 - 320x240 (small)", "url": "https://r7---sn-j5cax8pnpvo-x1x6.googlevideo.com/videoplayback?initcwndbps=1265000&signature=718854A8DA90DA5D33F764DA98474772507ACCB6.2B88B05352F22636F2C4177690AC69539792D249&dur=26.981&sver=3&sparams=dur%2Cid%2Cinitcwndbps%2Cip%2Cipbits%2Citag%2Clmt%2Cmime%2Cmm%2Cmn%2Cms%2Cmv%2Cpcm2%2Cpcm2cms%2Cpl%2Crequiressl%2Csource%2Cupn%2Cexpire&lmt=1430146564228523&pcm2=yes&pcm2cms=yes&mime=video%2F3gpp&ip=181.169.199.112&requiressl=yes&mm=31&source=youtube&pl=20&mn=sn-j5cax8pnpvo-x1x6&mt=1451805828&mv=m&id=o-ANhq0Qc3DOszJWfMJQXdPA_193KllZnyHQD-WPZ9G1-6&ms=au&expire=1451827480&key=yt6&upn=-PI7yCUmRHw&ipbits=0&itag=36&fexp=9407157%2C9412858%2C9413278%2C9416126%2C9418200%2C9420452%2C9422124%2C9422541%2C9422596%2C9422925%2C9423573%2C9423590%2C9423662%2C9424020%2C9425346%2C9426236&ratebypass=yes", "vcodec": " mp4a.40.2", "format_note": "small", "height": 240, "width": 320, "ext": "3gp", "filesize": null, "fps": null, "format_id": "36", "player_url": null, "acodec": "mp4v.20.3"}, {"http_headers": {"Accept-Charset": "ISO-8859-1,utf-8;q=0.7,*;q=0.7", "Accept-Language": "en-us,en;q=0.5", "Accept-Encoding": "gzip, deflate", "Accept": "text/html,application/xhtml+xml,application/xml;q=0.9,*/*;q=0.8", "User-Agent": "Mozilla/5.0 (X11; Linux x86_64; rv:10.0) Gecko/20150101 Firefox/20.0 (Chrome)"}, "tbr": null, "format": "5 - 400x240 (small)", "url": "https://r7---sn-j5cax8pnpvo-x1x6.googlevideo.com/videoplayback?initcwndbps=1265000&signature=6DA3419328266ACA760F11F67772BD19502B87.C2CE39360203EBC196F6F3CA25E070B8F9C21141&dur=26.854&sver=3&sparams=dur%2Cid%2Cinitcwndbps%2Cip%2Cipbits%2Citag%2Clmt%2Cmime%2Cmm%2Cmn%2Cms%2Cmv%2Cpcm2%2Cpcm2cms%2Cpl%2Crequiressl%2Csource%2Cupn%2Cexpire&lmt=1430146567548260&pcm2=yes&pcm2cms=yes&mime=video%2Fx-flv&ip=181.169.199.112&requiressl=yes&mm=31&source=youtube&pl=20&mn=sn-j5cax8pnpvo-x1x6&mt=1451805828&mv=m&id=o-ANhq0Qc3DOszJWfMJQXdPA_193KllZnyHQD-WPZ9G1-6&ms=au&expire=1451827480&key=yt6&upn=-PI7yCUmRHw&ipbits=0&itag=5&fexp=9407157%2C9412858%2C9413278%2C9416126%2C9418200%2C9420452%2C9422124%2C9422541%2C9422596%2C9422925%2C9423573%2C9423590%2C9423662%2C9424020%2C9425346%2C9426236&ratebypass=yes", "format_note": "small", "height": 240, "width": 400, "ext": "flv", "filesize": null, "fps": null, "format_id": "5", "player_url": null}, {"http_headers": {"Accept-Charset": "ISO-8859-1,utf-8;q=0.7,*;q=0.7", "Accept-Language": "en-us,en;q=0.5", "Accept-Encoding": "gzip, deflate", "Accept": "text/html,application/xhtml+xml,application/xml;q=0.9,*/*;q=0.8", "User-Agent": "Mozilla/5.0 (X11; Linux x86_64; rv:10.0) Gecko/20150101 Firefox/20.0 (Chrome)"}, "tbr": null, "format": "43 - 640x360 (medium)", "url": "https://r7---sn-j5cax8pnpvo-x1x6.googlevideo.com/videoplayback?initcwndbps=1265000&signature=7A977CCE9F5C3AC6F7E5C444BC477CF797C15092.6901715D01A5018C7B685FA2FCAC765AE295810B&dur=0.000&sver=3&sparams=dur%2Cid%2Cinitcwndbps%2Cip%2Cipbits%2Citag%2Clmt%2Cmime%2Cmm%2Cmn%2Cms%2Cmv%2Cpcm2%2Cpcm2cms%2Cpl%2Cratebypass%2Crequiressl%2Csource%2Cupn%2Cexpire&lmt=1430147490331992&pcm2=yes&pcm2cms=yes&mime=video%2Fwebm&ip=181.169.199.112&requiressl=yes&mm=31&source=youtube&pl=20&mn=sn-j5cax8pnpvo-x1x6&mt=1451805828&mv=m&id=o-ANhq0Qc3DOszJWfMJQXdPA_193KllZnyHQD-WPZ9G1-6&ms=au&expire=1451827480&key=yt6&upn=-PI7yCUmRHw&ratebypass=yes&ipbits=0&itag=43&fexp=9407157%2C9412858%2C9413278%2C9416126%2C9418200%2C9420452%2C9422124%2C9422541%2C9422596%2C9422925%2C9423573%2C9423590%2C9423662%2C9424020%2C9425346%2C9426236", "vcodec": " vorbis", "format_note": "medium", "height": 360, "width": 640, "ext": "webm", "filesize": null, "fps": null, "format_id": "43", "player_url": null, "acodec": "vp8.0"}, {"http_headers": {"Accept-Charset": "ISO-8859-1,utf-8;q=0.7,*;q=0.7", "Accept-Language": "en-us,en;q=0.5", "Accept-Encoding": "gzip, deflate", "Accept": "text/html,application/xhtml+xml,application/xml;q=0.9,*/*;q=0.8", "User-Agent": "Mozilla/5.0 (X11; Linux x86_64; rv:10.0) Gecko/20150101 Firefox/20.0 (Chrome)"}, "tbr": null, "format": "18 - 640x360 (medium)", "url": "https://r7---sn-j5cax8pnpvo-x1x6.googlevideo.com/videoplayback?initcwndbps=1265000&signature=61D7A392997777312916D48A6B8FA17122A6F126.316505F2E2189682F2DA70C55CC98573CE5B922C&dur=26.865&sver=3&sparams=dur%2Cid%2Cinitcwndbps%2Cip%2Cipbits%2Citag%2Clmt%2Cmime%2Cmm%2Cmn%2Cms%2Cmv%2Cpcm2%2Cpcm2cms%2Cpl%2Cratebypass%2Crequiressl%2Csource%2Cupn%2Cexpire&lmt=1430146577454964&pcm2=yes&pcm2cms=yes&mime=video%2Fmp4&ip=181.169.199.112&requiressl=yes&mm=31&source=youtube&pl=20&mn=sn-j5cax8pnpvo-x1x6&mt=1451805828&mv=m&id=o-ANhq0Qc3DOszJWfMJQXdPA_193KllZnyHQD-WPZ9G1-6&ms=au&expire=1451827480&key=yt6&upn=-PI7yCUmRHw&ratebypass=yes&ipbits=0&itag=18&fexp=9407157%2C9412858%2C9413278%2C9416126%2C9418200%2C9420452%2C9422124%2C9422541%2C9422596%2C9422925%2C9423573%2C9423590%2C9423662%2C9424020%2C9425346%2C9426236", "vcodec": " mp4a.40.2", "format_note": "medium", "height": 360, "width": 640, "ext": "mp4", "filesize": null, "fps": null, "format_id": "18", "player_url": null, "acodec": "avc1.42001E"}, {"http_headers": {"Accept-Charset": "ISO-8859-1,utf-8;q=0.7,*;q=0.7", "Accept-Language": "en-us,en;q=0.5", "Accept-Encoding": "gzip, deflate", "Accept": "text/html,application/xhtml+xml,application/xml;q=0.9,*/*;q=0.8", "User-Agent": "Mozilla/5.0 (X11; Linux x86_64; rv:10.0) Gecko/20150101 Firefox/20.0 (Chrome)"}, "tbr": null, "format": "22 - 1280x720 (hd720)", "url": "https://r7---sn-j5cax8pnpvo-x1x6.googlevideo.com/videoplayback?initcwndbps=1265000&signature=2EA1C733CFE6D8CC38E373F052383B46AB301FA5.AFE037D312FA552C270CDACD85899A537D6613A2&dur=26.865&sver=3&sparams=dur%2Cid%2Cinitcwndbps%2Cip%2Cipbits%2Citag%2Clmt%2Cmime%2Cmm%2Cmn%2Cms%2Cmv%2Cpcm2%2Cpcm2cms%2Cpl%2Cratebypass%2Crequiressl%2Csource%2Cupn%2Cexpire&lmt=1430146799200234&pcm2=yes&pcm2cms=yes&mime=video%2Fmp4&ip=181.169.199.112&requiressl=yes&mm=31&source=youtube&pl=20&mn=sn-j5cax8pnpvo-x1x6&mt=1451805828&mv=m&id=o-ANhq0Qc3DOszJWfMJQXdPA_193KllZnyHQD-WPZ9G1-6&ms=au&expire=1451827480&key=yt6&upn=-PI7yCUmRHw&ratebypass=yes&ipbits=0&itag=22&fexp=9407157%2C9412858%2C9413278%2C9416126%2C9418200%2C9420452%2C9422124%2C9422541%2C9422596%2C9422925%2C9423573%2C9423590%2C9423662%2C9424020%2C9425346%2C9426236", "vcodec": " mp4a.40.2", "format_note": "hd720", "height": 720, "width": 1280, "ext": "mp4", "filesize": null, "fps": null, "format_id": "22", "player_url": null, "acodec": "avc1.64001F"}], "width": 1280, "n_entries": 1785}