{"upload_date": "20130527", "creator": null, "format_note": "hd720", "height": 720, "thumbnail": "https://i.ytimg.com/vi/wus44wLMyYI/maxresdefault.jpg", "like_count": 1903, "duration": 229, "fulltitle": "Los Autenticos Decadentes - El Murguero - Encuentro en el Estudio [HD]", "playlist_index": 186, "view_count": 1069287, "playlist": "Uploads from EncuentroenelEstudio", "title": "Los Autenticos Decadentes - El Murguero - Encuentro en el Estudio [HD]", "_filename": "downloads\\EncuentroenelEstudio\\Los Autenticos Decadentes - El Murguero - Encuentro en el Estudio [HD]-wus44wLMyYI.mp4", "tags": ["Encuentro", "Ion", "live from abbey road", "La Brujula", "Ariel Hassan", "Lalo Mir", "Canal Encuentro", "Jorge Portugues Da Silva", "Rock Nacional", "Argentina", "Estudios ION", "Cucho", "Gustavo Parisi", "Jorge Serrano", "Gustavo Montecchia", "Diego Demarco", "Gast\u00f3n Bernardou", "Mart\u00edn Lorenzo", "Daniel Zimbello", "Pablo Armesto", "Pablo Rodr\u00edguez", "Eduardo Tr\u00edpodi", "Mariano Franceschelli", "Guillermo Eijo"], "is_live": null, "id": "wus44wLMyYI", "dislike_count": 44, "average_rating": 4.90960454941, "filesize": null, "fps": null, "age_limit": 0, "annotations": "<?xml version=\"1.0\" encoding=\"UTF-8\" ?><document><annotations></annotations></document>", "webpage_url_basename": "wus44wLMyYI", "acodec": "avc1.64001F", "display_id": "wus44wLMyYI", "automatic_captions": {}, "description": "Encuentro en el Estudio\nCanal Encuentro\nMinisterio de Educaci\u00f3n de la Naci\u00f3n\nRep\u00fablica Argentina\n\nConduccion\nLalo Mir\n\nIngeniero de grabacion\nJorge Portugues Da Silva\n\nIdea y Direccion\nAriel Hassan\nWoody Gonzalez\n\nDireccion de Fotografia\nFernando Nogueira\n\nProduccion Ejecutiva\nIara Uhalde\n\nCamaras:\nDaniel Panigazzi\nFernando Nogueira\nSantiago Nadra\nGustavo Cataldi\nJulian Chalde\n\nAsistentes tecnicos\nMatias Silveira\nGustavo Narvaez\n\nProduccion\nRita Medina\n\nEdicion\nAriel Hassan\nVirginia Ciccolella\nAdrian Mu\u00f1oz\n\nGuion\nIna Godoy\n\nMaquillaje\nConstanza Hazan\n\nVestuario\nSandra Fernandez\n\nFoto Fija\nLucia Galli\n\nAdministracion\nIrma Grosso\n\nProduccion General\nLa Brujula Television\n\n\nEstudios ION\n\nDireccion\nOsvaldo Acedo\n\nAsistentes\nHernan Grasso\nMariano Beyoglonian\nLeonardo Checchia", "format": "22 - 1280x720 (hd720)", "start_time": null, "tbr": null, "categories": ["Music"], "playlist_id": "UUEMAjQ5DvafKMRaHJwrTY2A", "uploader": "EncuentroenelEstudio", "format_id": "22", "uploader_id": "EncuentroenelEstudio", "subtitles": {}, "playlist_title": "Uploads from EncuentroenelEstudio", "thumbnails": [{"url": "https://i.ytimg.com/vi/wus44wLMyYI/maxresdefault.jpg", "id": "0"}], "alt_title": null, "url": "https://r5---sn-j5cax8pnpvo-x1xy.googlevideo.com/videoplayback?id=o-AA17iESiMA0NpN_0c_1ivpXwxbMwCvj8Nw75DuZDGgRD&itag=22&sver=3&ratebypass=yes&sparams=dur%2Cid%2Cinitcwndbps%2Cip%2Cipbits%2Citag%2Clmt%2Cmime%2Cmm%2Cmn%2Cms%2Cmv%2Cpcm2cms%2Cpl%2Cratebypass%2Crequiressl%2Csource%2Cupn%2Cexpire&ip=181.169.199.112&dur=228.577&key=yt6&lmt=1429702927384434&fexp=9406851%2C9407118%2C9408215%2C9416126%2C9416985%2C9418204%2C9418750%2C9418778%2C9420452%2C9421931%2C9422596%2C9423640%2C9423662%2C9425670%2C9425978%2C9426237&expire=1451005496&ipbits=0&initcwndbps=1273750&mime=video%2Fmp4&requiressl=yes&pcm2cms=yes&signature=5004EBDFB185A627714E5FD7EEFE5796B30878B0.CAE3E490A7CD7BB88DD7F171107BB71C0E7200C8&source=youtube&upn=wiCKDi0RSKM&ms=au&mv=m&pl=20&mt=1450983859&mn=sn-j5cax8pnpvo-x1xy&mm=31", "extractor_key": "Youtube", "vcodec": " mp4a.40.2", "http_headers": {"Accept-Charset": "ISO-8859-1,utf-8;q=0.7,*;q=0.7", "Accept-Language": "en-us,en;q=0.5", "Accept-Encoding": "gzip, deflate", "Accept": "text/html,application/xhtml+xml,application/xml;q=0.9,*/*;q=0.8", "User-Agent": "Mozilla/5.0 (X11; Linux x86_64; rv:10.0) Gecko/20150101 Firefox/20.0 (Chrome)"}, "player_url": null, "ext": "mp4", "extractor": "youtube", "end_time": null, "webpage_url": "https://www.youtube.com/watch?v=wus44wLMyYI", "formats": [{"asr": 44100, "tbr": 123, "format": "171 - audio only (DASH audio)", "url": "https://r5---sn-j5cax8pnpvo-x1xy.googlevideo.com/videoplayback?id=c2eb38e302ccc982&itag=171&source=youtube&requiressl=yes&mn=sn-j5cax8pnpvo-x1xy&mm=31&ms=au&mv=m&pl=20&ratebypass=yes&mime=audio/webm&gir=yes&clen=3343069&lmt=1449627903960034&dur=228.518&sver=3&signature=4D4D05C2C4189DCFE14F8264C82D7A939EEE12EF.4ABC3EFC9D7AB1D9050F9A2A6D61273053B96B55&fexp=9406851,9407118,9408215,9416126,9416985,9418204,9418750,9418778,9420452,9421931,9422596,9423640,9423662,9425670,9425978,9426237&key=dg_yt0&mt=1450983859&upn=BefEihsswL0&ip=181.169.199.112&ipbits=0&expire=1451005497&sparams=ip,ipbits,expire,id,itag,source,requiressl,mn,mm,ms,mv,pl,ratebypass,mime,gir,clen,lmt,dur", "vcodec": "none", "format_note": "DASH audio", "ext": "webm", "height": null, "width": null, "abr": 128, "preference": -50, "fps": null, "format_id": "171", "acodec": "vorbis", "http_headers": {"Accept-Charset": "ISO-8859-1,utf-8;q=0.7,*;q=0.7", "Accept-Language": "en-us,en;q=0.5", "Accept-Encoding": "gzip, deflate", "Accept": "text/html,application/xhtml+xml,application/xml;q=0.9,*/*;q=0.8", "User-Agent": "Mozilla/5.0 (X11; Linux x86_64; rv:10.0) Gecko/20150101 Firefox/20.0 (Chrome)"}, "filesize": 3343069}, {"asr": 44100, "tbr": 129, "container": "m4a_dash", "format": "140 - audio only (DASH audio)", "url": "https://r5---sn-j5cax8pnpvo-x1xy.googlevideo.com/videoplayback?id=c2eb38e302ccc982&itag=140&source=youtube&requiressl=yes&mn=sn-j5cax8pnpvo-x1xy&mm=31&ms=au&mv=m&pl=20&ratebypass=yes&mime=audio/mp4&gir=yes&clen=3670317&lmt=1429702531550251&dur=228.576&sver=3&signature=917EDC72114267605F3942AC90CD9B90E72211DB.253B830399C52F19508E51BECCB1FE7BF5F72BB2&fexp=9406851,9407118,9408215,9416126,9416985,9418204,9418750,9418778,9420452,9421931,9422596,9423640,9423662,9425670,9425978,9426237&key=dg_yt0&mt=1450983859&upn=BefEihsswL0&ip=181.169.199.112&ipbits=0&expire=1451005497&sparams=ip,ipbits,expire,id,itag,source,requiressl,mn,mm,ms,mv,pl,ratebypass,mime,gir,clen,lmt,dur", "filesize": 3670317, "vcodec": "none", "format_note": "DASH audio", "abr": 128, "height": null, "width": null, "ext": "m4a", "preference": -50, "fps": null, "format_id": "140", "http_headers": {"Accept-Charset": "ISO-8859-1,utf-8;q=0.7,*;q=0.7", "Accept-Language": "en-us,en;q=0.5", "Accept-Encoding": "gzip, deflate", "Accept": "text/html,application/xhtml+xml,application/xml;q=0.9,*/*;q=0.8", "User-Agent": "Mozilla/5.0 (X11; Linux x86_64; rv:10.0) Gecko/20150101 Firefox/20.0 (Chrome)"}, "acodec": "aac"}, {"asr": 44100, "tbr": 255, "container": "m4a_dash", "format": "141 - audio only (DASH audio)", "url": "https://r5---sn-j5cax8pnpvo-x1xy.googlevideo.com/videoplayback?id=c2eb38e302ccc982&itag=141&source=youtube&requiressl=yes&mn=sn-j5cax8pnpvo-x1xy&mm=31&ms=au&mv=m&pl=20&ratebypass=yes&mime=audio/mp4&gir=yes&clen=7288139&lmt=1429702533907813&dur=228.577&sver=3&signature=4D11704D9FE93D2049FE8ACC97F9ED4226A65616.496554ED65C8678D21B082B1EDCF9CA5AC9B328A&fexp=9406851,9407118,9408215,9416126,9416985,9418204,9418750,9418778,9420452,9421931,9422596,9423640,9423662,9425670,9425978,9426237&key=dg_yt0&mt=1450983859&upn=BefEihsswL0&ip=181.169.199.112&ipbits=0&expire=1451005497&sparams=ip,ipbits,expire,id,itag,source,requiressl,mn,mm,ms,mv,pl,ratebypass,mime,gir,clen,lmt,dur", "filesize": 7288139, "vcodec": "none", "format_note": "DASH audio", "abr": 256, "height": null, "width": null, "ext": "m4a", "preference": -50, "fps": null, "format_id": "141", "http_headers": {"Accept-Charset": "ISO-8859-1,utf-8;q=0.7,*;q=0.7", "Accept-Language": "en-us,en;q=0.5", "Accept-Encoding": "gzip, deflate", "Accept": "text/html,application/xhtml+xml,application/xml;q=0.9,*/*;q=0.8", "User-Agent": "Mozilla/5.0 (X11; Linux x86_64; rv:10.0) Gecko/20150101 Firefox/20.0 (Chrome)"}, "acodec": "aac"}, {"asr": null, "tbr": 110, "format": "160 - 256x144 (DASH video)", "url": "https://r5---sn-j5cax8pnpvo-x1xy.googlevideo.com/videoplayback?id=c2eb38e302ccc982&itag=160&source=youtube&requiressl=yes&mn=sn-j5cax8pnpvo-x1xy&mm=31&ms=au&mv=m&pl=20&ratebypass=yes&mime=video/mp4&gir=yes&clen=3110565&lmt=1429702598908467&dur=228.560&sver=3&signature=62C28C9DF2EB0475284DC5613D1B3FD5ECD06FFF.53CAF2385A7295AA246B002726AF95D8BED4A2F1&fexp=9406851,9407118,9408215,9416126,9416985,9418204,9418750,9418778,9420452,9421931,9422596,9423640,9423662,9425670,9425978,9426237&key=dg_yt0&mt=1450983859&upn=BefEihsswL0&ip=181.169.199.112&ipbits=0&expire=1451005497&sparams=ip,ipbits,expire,id,itag,source,requiressl,mn,mm,ms,mv,pl,ratebypass,mime,gir,clen,lmt,dur", "filesize": 3110565, "vcodec": "avc1.4d400c", "format_note": "DASH video", "height": 144, "width": 256, "ext": "mp4", "preference": -40, "fps": 13, "format_id": "160", "http_headers": {"Accept-Charset": "ISO-8859-1,utf-8;q=0.7,*;q=0.7", "Accept-Language": "en-us,en;q=0.5", "Accept-Encoding": "gzip, deflate", "Accept": "text/html,application/xhtml+xml,application/xml;q=0.9,*/*;q=0.8", "User-Agent": "Mozilla/5.0 (X11; Linux x86_64; rv:10.0) Gecko/20150101 Firefox/20.0 (Chrome)"}, "acodec": "none"}, {"asr": null, "tbr": 120, "container": "webm", "format": "278 - 256x144 (DASH video)", "url": "https://r5---sn-j5cax8pnpvo-x1xy.googlevideo.com/videoplayback?id=c2eb38e302ccc982&itag=278&source=youtube&requiressl=yes&mn=sn-j5cax8pnpvo-x1xy&mm=31&ms=au&mv=m&pl=20&ratebypass=yes&mime=video/webm&gir=yes&clen=3012137&lmt=1449634415689284&dur=228.480&sver=3&signature=0E6932444BA489C8166BAFD0612726F6C1D7E85A.22E2304E49481A2B6F4EFFDB25DC6BB0D06F8C35&fexp=9406851,9407118,9408215,9416126,9416985,9418204,9418750,9418778,9420452,9421931,9422596,9423640,9423662,9425670,9425978,9426237&key=dg_yt0&mt=1450983859&upn=BefEihsswL0&ip=181.169.199.112&ipbits=0&expire=1451005497&sparams=ip,ipbits,expire,id,itag,source,requiressl,mn,mm,ms,mv,pl,ratebypass,mime,gir,clen,lmt,dur", "filesize": 3012137, "vcodec": "vp9", "format_note": "DASH video", "height": 144, "width": 256, "ext": "webm", "preference": -40, "fps": 13, "format_id": "278", "http_headers": {"Accept-Charset": "ISO-8859-1,utf-8;q=0.7,*;q=0.7", "Accept-Language": "en-us,en;q=0.5", "Accept-Encoding": "gzip, deflate", "Accept": "text/html,application/xhtml+xml,application/xml;q=0.9,*/*;q=0.8", "User-Agent": "Mozilla/5.0 (X11; Linux x86_64; rv:10.0) Gecko/20150101 Firefox/20.0 (Chrome)"}, "acodec": "none"}, {"asr": null, "tbr": 256, "format": "133 - 426x240 (DASH video)", "url": "https://r5---sn-j5cax8pnpvo-x1xy.googlevideo.com/videoplayback?id=c2eb38e302ccc982&itag=133&source=youtube&requiressl=yes&mn=sn-j5cax8pnpvo-x1xy&mm=31&ms=au&mv=m&pl=20&ratebypass=yes&mime=video/mp4&gir=yes&clen=6983055&lmt=1429702603155835&dur=228.520&sver=3&signature=2E41D58B5C725A9BFF10A168C1E9421610E9A345.10DFA535EF2BE2DCE5263AEE7D7F2D00D07DF5EB&fexp=9406851,9407118,9408215,9416126,9416985,9418204,9418750,9418778,9420452,9421931,9422596,9423640,9423662,9425670,9425978,9426237&key=dg_yt0&mt=1450983859&upn=BefEihsswL0&ip=181.169.199.112&ipbits=0&expire=1451005497&sparams=ip,ipbits,expire,id,itag,source,requiressl,mn,mm,ms,mv,pl,ratebypass,mime,gir,clen,lmt,dur", "filesize": 6983055, "vcodec": "avc1.4d4015", "format_note": "DASH video", "height": 240, "width": 426, "ext": "mp4", "preference": -40, "fps": 25, "format_id": "133", "http_headers": {"Accept-Charset": "ISO-8859-1,utf-8;q=0.7,*;q=0.7", "Accept-Language": "en-us,en;q=0.5", "Accept-Encoding": "gzip, deflate", "Accept": "text/html,application/xhtml+xml,application/xml;q=0.9,*/*;q=0.8", "User-Agent": "Mozilla/5.0 (X11; Linux x86_64; rv:10.0) Gecko/20150101 Firefox/20.0 (Chrome)"}, "acodec": "none"}, {"asr": null, "tbr": 267, "format": "242 - 426x240 (DASH video)", "url": "https://r5---sn-j5cax8pnpvo-x1xy.googlevideo.com/videoplayback?id=c2eb38e302ccc982&itag=242&source=youtube&requiressl=yes&mn=sn-j5cax8pnpvo-x1xy&mm=31&ms=au&mv=m&pl=20&ratebypass=yes&mime=video/webm&gir=yes&clen=6769992&lmt=1449634426581456&dur=228.480&sver=3&signature=0ED789A3D0DA9B7F7093E0D9ACC1E76109F65A64.77C8AE47EF98FE58ADEF72355271D161A268BC16&fexp=9406851,9407118,9408215,9416126,9416985,9418204,9418750,9418778,9420452,9421931,9422596,9423640,9423662,9425670,9425978,9426237&key=dg_yt0&mt=1450983859&upn=BefEihsswL0&ip=181.169.199.112&ipbits=0&expire=1451005497&sparams=ip,ipbits,expire,id,itag,source,requiressl,mn,mm,ms,mv,pl,ratebypass,mime,gir,clen,lmt,dur", "filesize": 6769992, "vcodec": "vp9", "format_note": "DASH video", "height": 240, "width": 426, "ext": "webm", "preference": -40, "fps": 25, "format_id": "242", "http_headers": {"Accept-Charset": "ISO-8859-1,utf-8;q=0.7,*;q=0.7", "Accept-Language": "en-us,en;q=0.5", "Accept-Encoding": "gzip, deflate", "Accept": "text/html,application/xhtml+xml,application/xml;q=0.9,*/*;q=0.8", "User-Agent": "Mozilla/5.0 (X11; Linux x86_64; rv:10.0) Gecko/20150101 Firefox/20.0 (Chrome)"}, "acodec": "none"}, {"asr": null, "tbr": 487, "format": "243 - 640x360 (DASH video)", "url": "https://r5---sn-j5cax8pnpvo-x1xy.googlevideo.com/videoplayback?id=c2eb38e302ccc982&itag=243&source=youtube&requiressl=yes&mn=sn-j5cax8pnpvo-x1xy&mm=31&ms=au&mv=m&pl=20&ratebypass=yes&mime=video/webm&gir=yes&clen=12539794&lmt=1449634415149941&dur=228.480&sver=3&signature=394EA80D253D399F2F56F706A46C39B68CA8A54B.5E5D4468EE5F28138D2F5019638589D20111B32B&fexp=9406851,9407118,9408215,9416126,9416985,9418204,9418750,9418778,9420452,9421931,9422596,9423640,9423662,9425670,9425978,9426237&key=dg_yt0&mt=1450983859&upn=BefEihsswL0&ip=181.169.199.112&ipbits=0&expire=1451005497&sparams=ip,ipbits,expire,id,itag,source,requiressl,mn,mm,ms,mv,pl,ratebypass,mime,gir,clen,lmt,dur", "filesize": 12539794, "vcodec": "vp9", "format_note": "DASH video", "height": 360, "width": 640, "ext": "webm", "preference": -40, "fps": 25, "format_id": "243", "http_headers": {"Accept-Charset": "ISO-8859-1,utf-8;q=0.7,*;q=0.7", "Accept-Language": "en-us,en;q=0.5", "Accept-Encoding": "gzip, deflate", "Accept": "text/html,application/xhtml+xml,application/xml;q=0.9,*/*;q=0.8", "User-Agent": "Mozilla/5.0 (X11; Linux x86_64; rv:10.0) Gecko/20150101 Firefox/20.0 (Chrome)"}, "acodec": "none"}, {"asr": null, "tbr": 607, "format": "134 - 640x360 (DASH video)", "url": "https://r5---sn-j5cax8pnpvo-x1xy.googlevideo.com/videoplayback?id=c2eb38e302ccc982&itag=134&source=youtube&requiressl=yes&mn=sn-j5cax8pnpvo-x1xy&mm=31&ms=au&mv=m&pl=20&ratebypass=yes&mime=video/mp4&gir=yes&clen=16725595&lmt=1429702611541930&dur=228.520&sver=3&signature=0E773FAABC76C3E01CA1240B26800AED1B8657A2.2242F7615CF1A483D27703025B8786823448C8CE&fexp=9406851,9407118,9408215,9416126,9416985,9418204,9418750,9418778,9420452,9421931,9422596,9423640,9423662,9425670,9425978,9426237&key=dg_yt0&mt=1450983859&upn=BefEihsswL0&ip=181.169.199.112&ipbits=0&expire=1451005497&sparams=ip,ipbits,expire,id,itag,source,requiressl,mn,mm,ms,mv,pl,ratebypass,mime,gir,clen,lmt,dur", "filesize": 16725595, "vcodec": "avc1.4d401e", "format_note": "DASH video", "height": 360, "width": 640, "ext": "mp4", "preference": -40, "fps": 25, "format_id": "134", "http_headers": {"Accept-Charset": "ISO-8859-1,utf-8;q=0.7,*;q=0.7", "Accept-Language": "en-us,en;q=0.5", "Accept-Encoding": "gzip, deflate", "Accept": "text/html,application/xhtml+xml,application/xml;q=0.9,*/*;q=0.8", "User-Agent": "Mozilla/5.0 (X11; Linux x86_64; rv:10.0) Gecko/20150101 Firefox/20.0 (Chrome)"}, "acodec": "none"}, {"asr": null, "tbr": 915, "format": "244 - 854x480 (DASH video)", "url": "https://r5---sn-j5cax8pnpvo-x1xy.googlevideo.com/videoplayback?id=c2eb38e302ccc982&itag=244&source=youtube&requiressl=yes&mn=sn-j5cax8pnpvo-x1xy&mm=31&ms=au&mv=m&pl=20&ratebypass=yes&mime=video/webm&gir=yes&clen=23170338&lmt=1449634428739580&dur=228.480&sver=3&signature=747CEB3801612A6A5C8B1FBA32C0077CCD7C3131.635B0A4C1CA2691D09A8DFAE4A9BF386D82C37A2&fexp=9406851,9407118,9408215,9416126,9416985,9418204,9418750,9418778,9420452,9421931,9422596,9423640,9423662,9425670,9425978,9426237&key=dg_yt0&mt=1450983859&upn=BefEihsswL0&ip=181.169.199.112&ipbits=0&expire=1451005497&sparams=ip,ipbits,expire,id,itag,source,requiressl,mn,mm,ms,mv,pl,ratebypass,mime,gir,clen,lmt,dur", "filesize": 23170338, "vcodec": "vp9", "format_note": "DASH video", "height": 480, "width": 854, "ext": "webm", "preference": -40, "fps": 25, "format_id": "244", "http_headers": {"Accept-Charset": "ISO-8859-1,utf-8;q=0.7,*;q=0.7", "Accept-Language": "en-us,en;q=0.5", "Accept-Encoding": "gzip, deflate", "Accept": "text/html,application/xhtml+xml,application/xml;q=0.9,*/*;q=0.8", "User-Agent": "Mozilla/5.0 (X11; Linux x86_64; rv:10.0) Gecko/20150101 Firefox/20.0 (Chrome)"}, "acodec": "none"}, {"asr": null, "tbr": 1110, "format": "135 - 854x480 (DASH video)", "url": "https://r5---sn-j5cax8pnpvo-x1xy.googlevideo.com/videoplayback?id=c2eb38e302ccc982&itag=135&source=youtube&requiressl=yes&mn=sn-j5cax8pnpvo-x1xy&mm=31&ms=au&mv=m&pl=20&ratebypass=yes&mime=video/mp4&gir=yes&clen=30645528&lmt=1429702714550706&dur=228.520&sver=3&signature=6042570059BA8B58C466DEC7653E3DFB4B167066.70DA4CD829C513E2B6228E7DC0AB6CC2F98C0A84&fexp=9406851,9407118,9408215,9416126,9416985,9418204,9418750,9418778,9420452,9421931,9422596,9423640,9423662,9425670,9425978,9426237&key=dg_yt0&mt=1450983859&upn=BefEihsswL0&ip=181.169.199.112&ipbits=0&expire=1451005497&sparams=ip,ipbits,expire,id,itag,source,requiressl,mn,mm,ms,mv,pl,ratebypass,mime,gir,clen,lmt,dur", "filesize": 30645528, "vcodec": "avc1.4d401e", "format_note": "DASH video", "height": 480, "width": 854, "ext": "mp4", "preference": -40, "fps": 25, "format_id": "135", "http_headers": {"Accept-Charset": "ISO-8859-1,utf-8;q=0.7,*;q=0.7", "Accept-Language": "en-us,en;q=0.5", "Accept-Encoding": "gzip, deflate", "Accept": "text/html,application/xhtml+xml,application/xml;q=0.9,*/*;q=0.8", "User-Agent": "Mozilla/5.0 (X11; Linux x86_64; rv:10.0) Gecko/20150101 Firefox/20.0 (Chrome)"}, "acodec": "none"}, {"asr": null, "tbr": 1727, "format": "247 - 1280x720 (DASH video)", "url": "https://r5---sn-j5cax8pnpvo-x1xy.googlevideo.com/videoplayback?id=c2eb38e302ccc982&itag=247&source=youtube&requiressl=yes&mn=sn-j5cax8pnpvo-x1xy&mm=31&ms=au&mv=m&pl=20&ratebypass=yes&mime=video/webm&gir=yes&clen=44873988&lmt=1449634418854637&dur=228.480&sver=3&signature=069D5F90BAF7D36EC3AA6E7BAC95907ADB0B2A44.75AD7865CD4BDFF1789FF7857E62831CA802C9B3&fexp=9406851,9407118,9408215,9416126,9416985,9418204,9418750,9418778,9420452,9421931,9422596,9423640,9423662,9425670,9425978,9426237&key=dg_yt0&mt=1450983859&upn=BefEihsswL0&ip=181.169.199.112&ipbits=0&expire=1451005497&sparams=ip,ipbits,expire,id,itag,source,requiressl,mn,mm,ms,mv,pl,ratebypass,mime,gir,clen,lmt,dur", "filesize": 44873988, "vcodec": "vp9", "format_note": "DASH video", "height": 720, "width": 1280, "ext": "webm", "preference": -40, "fps": 25, "format_id": "247", "http_headers": {"Accept-Charset": "ISO-8859-1,utf-8;q=0.7,*;q=0.7", "Accept-Language": "en-us,en;q=0.5", "Accept-Encoding": "gzip, deflate", "Accept": "text/html,application/xhtml+xml,application/xml;q=0.9,*/*;q=0.8", "User-Agent": "Mozilla/5.0 (X11; Linux x86_64; rv:10.0) Gecko/20150101 Firefox/20.0 (Chrome)"}, "acodec": "none"}, {"asr": null, "tbr": 2217, "format": "136 - 1280x720 (DASH video)", "url": "https://r5---sn-j5cax8pnpvo-x1xy.googlevideo.com/videoplayback?id=c2eb38e302ccc982&itag=136&source=youtube&requiressl=yes&mn=sn-j5cax8pnpvo-x1xy&mm=31&ms=au&mv=m&pl=20&ratebypass=yes&mime=video/mp4&gir=yes&clen=58595334&lmt=1429703164786254&dur=228.520&sver=3&signature=23BBA893D9ED6B729D96E1D9CF149F8E1BA8D8D0.192AA2AC28041BE32A6B7349E8138867DFD5B5C1&fexp=9406851,9407118,9408215,9416126,9416985,9418204,9418750,9418778,9420452,9421931,9422596,9423640,9423662,9425670,9425978,9426237&key=dg_yt0&mt=1450983859&upn=BefEihsswL0&ip=181.169.199.112&ipbits=0&expire=1451005497&sparams=ip,ipbits,expire,id,itag,source,requiressl,mn,mm,ms,mv,pl,ratebypass,mime,gir,clen,lmt,dur", "filesize": 58595334, "vcodec": "avc1.4d401f", "format_note": "DASH video", "height": 720, "width": 1280, "ext": "mp4", "preference": -40, "fps": 25, "format_id": "136", "http_headers": {"Accept-Charset": "ISO-8859-1,utf-8;q=0.7,*;q=0.7", "Accept-Language": "en-us,en;q=0.5", "Accept-Encoding": "gzip, deflate", "Accept": "text/html,application/xhtml+xml,application/xml;q=0.9,*/*;q=0.8", "User-Agent": "Mozilla/5.0 (X11; Linux x86_64; rv:10.0) Gecko/20150101 Firefox/20.0 (Chrome)"}, "acodec": "none"}, {"http_headers": {"Accept-Charset": "ISO-8859-1,utf-8;q=0.7,*;q=0.7", "Accept-Language": "en-us,en;q=0.5", "Accept-Encoding": "gzip, deflate", "Accept": "text/html,application/xhtml+xml,application/xml;q=0.9,*/*;q=0.8", "User-Agent": "Mozilla/5.0 (X11; Linux x86_64; rv:10.0) Gecko/20150101 Firefox/20.0 (Chrome)"}, "tbr": null, "format": "17 - 176x144 (small)", "url": "https://r5---sn-j5cax8pnpvo-x1xy.googlevideo.com/videoplayback?id=o-AA17iESiMA0NpN_0c_1ivpXwxbMwCvj8Nw75DuZDGgRD&itag=17&sver=3&sparams=dur%2Cid%2Cinitcwndbps%2Cip%2Cipbits%2Citag%2Clmt%2Cmime%2Cmm%2Cmn%2Cms%2Cmv%2Cpcm2cms%2Cpl%2Crequiressl%2Csource%2Cupn%2Cexpire&ip=181.169.199.112&dur=228.902&key=yt6&lmt=1394287633661475&fexp=9406851%2C9407118%2C9408215%2C9416126%2C9416985%2C9418204%2C9418750%2C9418778%2C9420452%2C9421931%2C9422596%2C9423640%2C9423662%2C9425670%2C9425978%2C9426237&expire=1451005496&ipbits=0&initcwndbps=1273750&mime=video%2F3gpp&requiressl=yes&pcm2cms=yes&signature=B2DF33B71587AE9CFF16B4780E3370D99B96B3CD.054C686E4A5F98EB9407E2A3087679F40E9D24ED&source=youtube&upn=wiCKDi0RSKM&ms=au&mv=m&pl=20&mt=1450983859&mn=sn-j5cax8pnpvo-x1xy&mm=31&ratebypass=yes", "vcodec": " mp4a.40.2", "format_note": "small", "height": 144, "width": 176, "ext": "3gp", "filesize": null, "fps": null, "format_id": "17", "player_url": null, "acodec": "mp4v.20.3"}, {"http_headers": {"Accept-Charset": "ISO-8859-1,utf-8;q=0.7,*;q=0.7", "Accept-Language": "en-us,en;q=0.5", "Accept-Encoding": "gzip, deflate", "Accept": "text/html,application/xhtml+xml,application/xml;q=0.9,*/*;q=0.8", "User-Agent": "Mozilla/5.0 (X11; Linux x86_64; rv:10.0) Gecko/20150101 Firefox/20.0 (Chrome)"}, "tbr": null, "format": "36 - 320x240 (small)", "url": "https://r5---sn-j5cax8pnpvo-x1xy.googlevideo.com/videoplayback?id=o-AA17iESiMA0NpN_0c_1ivpXwxbMwCvj8Nw75DuZDGgRD&itag=36&sver=3&sparams=dur%2Cid%2Cinitcwndbps%2Cip%2Cipbits%2Citag%2Clmt%2Cmime%2Cmm%2Cmn%2Cms%2Cmv%2Cpcm2cms%2Cpl%2Crequiressl%2Csource%2Cupn%2Cexpire&ip=181.169.199.112&dur=228.762&key=yt6&lmt=1394287677748512&fexp=9406851%2C9407118%2C9408215%2C9416126%2C9416985%2C9418204%2C9418750%2C9418778%2C9420452%2C9421931%2C9422596%2C9423640%2C9423662%2C9425670%2C9425978%2C9426237&expire=1451005496&ipbits=0&initcwndbps=1273750&mime=video%2F3gpp&requiressl=yes&pcm2cms=yes&signature=55D23766CA18CA75F631A1569DB48EB2F81CEDCD.7926A9CEB0136251914C20B682336984179BF92A&source=youtube&upn=wiCKDi0RSKM&ms=au&mv=m&pl=20&mt=1450983859&mn=sn-j5cax8pnpvo-x1xy&mm=31&ratebypass=yes", "vcodec": " mp4a.40.2", "format_note": "small", "height": 240, "width": 320, "ext": "3gp", "filesize": null, "fps": null, "format_id": "36", "player_url": null, "acodec": "mp4v.20.3"}, {"http_headers": {"Accept-Charset": "ISO-8859-1,utf-8;q=0.7,*;q=0.7", "Accept-Language": "en-us,en;q=0.5", "Accept-Encoding": "gzip, deflate", "Accept": "text/html,application/xhtml+xml,application/xml;q=0.9,*/*;q=0.8", "User-Agent": "Mozilla/5.0 (X11; Linux x86_64; rv:10.0) Gecko/20150101 Firefox/20.0 (Chrome)"}, "tbr": null, "format": "5 - 400x240 (small)", "url": "https://r5---sn-j5cax8pnpvo-x1xy.googlevideo.com/videoplayback?id=o-AA17iESiMA0NpN_0c_1ivpXwxbMwCvj8Nw75DuZDGgRD&itag=5&sver=3&sparams=dur%2Cid%2Cinitcwndbps%2Cip%2Cipbits%2Citag%2Clmt%2Cmime%2Cmm%2Cmn%2Cms%2Cmv%2Cpcm2cms%2Cpl%2Crequiressl%2Csource%2Cupn%2Cexpire&ip=181.169.199.112&dur=228.597&key=yt6&lmt=1394287606288335&fexp=9406851%2C9407118%2C9408215%2C9416126%2C9416985%2C9418204%2C9418750%2C9418778%2C9420452%2C9421931%2C9422596%2C9423640%2C9423662%2C9425670%2C9425978%2C9426237&expire=1451005496&ipbits=0&initcwndbps=1273750&mime=video%2Fx-flv&requiressl=yes&pcm2cms=yes&signature=648DE0BF5568A8D6B75D7D7ED924029162688E59.553328D17019847BC62E6651E78D5D2568260914&source=youtube&upn=wiCKDi0RSKM&ms=au&mv=m&pl=20&mt=1450983859&mn=sn-j5cax8pnpvo-x1xy&mm=31&ratebypass=yes", "format_note": "small", "height": 240, "width": 400, "ext": "flv", "filesize": null, "fps": null, "format_id": "5", "player_url": null}, {"http_headers": {"Accept-Charset": "ISO-8859-1,utf-8;q=0.7,*;q=0.7", "Accept-Language": "en-us,en;q=0.5", "Accept-Encoding": "gzip, deflate", "Accept": "text/html,application/xhtml+xml,application/xml;q=0.9,*/*;q=0.8", "User-Agent": "Mozilla/5.0 (X11; Linux x86_64; rv:10.0) Gecko/20150101 Firefox/20.0 (Chrome)"}, "tbr": null, "format": "43 - 640x360 (medium)", "url": "https://r5---sn-j5cax8pnpvo-x1xy.googlevideo.com/videoplayback?id=o-AA17iESiMA0NpN_0c_1ivpXwxbMwCvj8Nw75DuZDGgRD&itag=43&sver=3&ratebypass=yes&sparams=dur%2Cid%2Cinitcwndbps%2Cip%2Cipbits%2Citag%2Clmt%2Cmime%2Cmm%2Cmn%2Cms%2Cmv%2Cpcm2cms%2Cpl%2Cratebypass%2Crequiressl%2Csource%2Cupn%2Cexpire&ip=181.169.199.112&dur=0.000&key=yt6&lmt=1368690877080145&fexp=9406851%2C9407118%2C9408215%2C9416126%2C9416985%2C9418204%2C9418750%2C9418778%2C9420452%2C9421931%2C9422596%2C9423640%2C9423662%2C9425670%2C9425978%2C9426237&expire=1451005496&ipbits=0&initcwndbps=1273750&mime=video%2Fwebm&requiressl=yes&pcm2cms=yes&signature=2DBD0F6BF5CEF45F2D5DFB087BBA407934828459.6926CFE9DB07B7C107B0BB88A7A36EE2FEEBA2F2&source=youtube&upn=wiCKDi0RSKM&ms=au&mv=m&pl=20&mt=1450983859&mn=sn-j5cax8pnpvo-x1xy&mm=31", "vcodec": " vorbis", "format_note": "medium", "height": 360, "width": 640, "ext": "webm", "filesize": null, "fps": null, "format_id": "43", "player_url": null, "acodec": "vp8.0"}, {"http_headers": {"Accept-Charset": "ISO-8859-1,utf-8;q=0.7,*;q=0.7", "Accept-Language": "en-us,en;q=0.5", "Accept-Encoding": "gzip, deflate", "Accept": "text/html,application/xhtml+xml,application/xml;q=0.9,*/*;q=0.8", "User-Agent": "Mozilla/5.0 (X11; Linux x86_64; rv:10.0) Gecko/20150101 Firefox/20.0 (Chrome)"}, "tbr": null, "format": "18 - 640x360 (medium)", "url": "https://r5---sn-j5cax8pnpvo-x1xy.googlevideo.com/videoplayback?id=o-AA17iESiMA0NpN_0c_1ivpXwxbMwCvj8Nw75DuZDGgRD&itag=18&sver=3&ratebypass=yes&sparams=dur%2Cid%2Cinitcwndbps%2Cip%2Cipbits%2Citag%2Clmt%2Cmime%2Cmm%2Cmn%2Cms%2Cmv%2Cpcm2cms%2Cpl%2Cratebypass%2Crequiressl%2Csource%2Cupn%2Cexpire&ip=181.169.199.112&dur=228.577&key=yt6&lmt=1429702726683538&fexp=9406851%2C9407118%2C9408215%2C9416126%2C9416985%2C9418204%2C9418750%2C9418778%2C9420452%2C9421931%2C9422596%2C9423640%2C9423662%2C9425670%2C9425978%2C9426237&expire=1451005496&ipbits=0&initcwndbps=1273750&mime=video%2Fmp4&requiressl=yes&pcm2cms=yes&signature=321757CD6A0057AF5CC2065BE63B27B49754023B.22D22E61A0B4CD34D49AF30F2B36271E7E27F1FB&source=youtube&upn=wiCKDi0RSKM&ms=au&mv=m&pl=20&mt=1450983859&mn=sn-j5cax8pnpvo-x1xy&mm=31", "vcodec": " mp4a.40.2", "format_note": "medium", "height": 360, "width": 640, "ext": "mp4", "filesize": null, "fps": null, "format_id": "18", "player_url": null, "acodec": "avc1.42001E"}, {"http_headers": {"Accept-Charset": "ISO-8859-1,utf-8;q=0.7,*;q=0.7", "Accept-Language": "en-us,en;q=0.5", "Accept-Encoding": "gzip, deflate", "Accept": "text/html,application/xhtml+xml,application/xml;q=0.9,*/*;q=0.8", "User-Agent": "Mozilla/5.0 (X11; Linux x86_64; rv:10.0) Gecko/20150101 Firefox/20.0 (Chrome)"}, "tbr": null, "format": "22 - 1280x720 (hd720)", "url": "https://r5---sn-j5cax8pnpvo-x1xy.googlevideo.com/videoplayback?id=o-AA17iESiMA0NpN_0c_1ivpXwxbMwCvj8Nw75DuZDGgRD&itag=22&sver=3&ratebypass=yes&sparams=dur%2Cid%2Cinitcwndbps%2Cip%2Cipbits%2Citag%2Clmt%2Cmime%2Cmm%2Cmn%2Cms%2Cmv%2Cpcm2cms%2Cpl%2Cratebypass%2Crequiressl%2Csource%2Cupn%2Cexpire&ip=181.169.199.112&dur=228.577&key=yt6&lmt=1429702927384434&fexp=9406851%2C9407118%2C9408215%2C9416126%2C9416985%2C9418204%2C9418750%2C9418778%2C9420452%2C9421931%2C9422596%2C9423640%2C9423662%2C9425670%2C9425978%2C9426237&expire=1451005496&ipbits=0&initcwndbps=1273750&mime=video%2Fmp4&requiressl=yes&pcm2cms=yes&signature=5004EBDFB185A627714E5FD7EEFE5796B30878B0.CAE3E490A7CD7BB88DD7F171107BB71C0E7200C8&source=youtube&upn=wiCKDi0RSKM&ms=au&mv=m&pl=20&mt=1450983859&mn=sn-j5cax8pnpvo-x1xy&mm=31", "vcodec": " mp4a.40.2", "format_note": "hd720", "height": 720, "width": 1280, "ext": "mp4", "filesize": null, "fps": null, "format_id": "22", "player_url": null, "acodec": "avc1.64001F"}], "width": 1280, "n_entries": 701}